setup.cfg
setup.py
pynos/__init__.py
pynos/device.py
pynos/exceptions.py
pynos/utilities.py
pynos.egg-info/PKG-INFO
pynos.egg-info/SOURCES.txt
pynos.egg-info/dependency_links.txt
pynos.egg-info/requires.txt
pynos.egg-info/top_level.txt
pynos/versions/__init__.py
pynos/versions/base/__init__.py
pynos/versions/base/bgp.py
pynos/versions/base/fabric_service.py
pynos/versions/base/firmware.py
pynos/versions/base/interface.py
pynos/versions/base/lldp.py
pynos/versions/base/ras.py
pynos/versions/base/services.py
pynos/versions/base/snmp.py
pynos/versions/base/system.py
pynos/versions/base/vcs.py
pynos/versions/base/yang/__init__.py
pynos/versions/base/yang/brocade_aaa.py
pynos/versions/base/yang/brocade_aaa_ext.py
pynos/versions/base/yang/brocade_arp.py
pynos/versions/base/yang/brocade_bprate_limit.py
pynos/versions/base/yang/brocade_cee_map.py
pynos/versions/base/yang/brocade_chassis.py
pynos/versions/base/yang/brocade_clock.py
pynos/versions/base/yang/brocade_common_def.py
pynos/versions/base/yang/brocade_diagnostics.py
pynos/versions/base/yang/brocade_dot1x.py
pynos/versions/base/yang/brocade_entity.py
pynos/versions/base/yang/brocade_fabric_service.py
pynos/versions/base/yang/brocade_fc_auth.py
pynos/versions/base/yang/brocade_fcoe.py
pynos/versions/base/yang/brocade_fcoe_ext.py
pynos/versions/base/yang/brocade_firmware.py
pynos/versions/base/yang/brocade_firmware_ext.py
pynos/versions/base/yang/brocade_ha.py
pynos/versions/base/yang/brocade_hardware.py
pynos/versions/base/yang/brocade_http_config.py
pynos/versions/base/yang/brocade_http_redirect.py
pynos/versions/base/yang/brocade_igmp_snooping.py
pynos/versions/base/yang/brocade_interface.py
pynos/versions/base/yang/brocade_interface_ext.py
pynos/versions/base/yang/brocade_intf_loopback.py
pynos/versions/base/yang/brocade_ip_access_list.py
pynos/versions/base/yang/brocade_ip_policy.py
pynos/versions/base/yang/brocade_ipv6_access_list.py
pynos/versions/base/yang/brocade_lacp.py
pynos/versions/base/yang/brocade_lag.py
pynos/versions/base/yang/brocade_license.py
pynos/versions/base/yang/brocade_lldp_ext.py
pynos/versions/base/yang/brocade_mac_access_list.py
