Metadata-Version: 1.1
Name: pynos
Version: 1.3.27
Summary: Brocade NOS Library.
Home-page: https://github.com/brocade/pynos
Author: Brocade Communications Systems, Inc.
Author-email: mstone@brocade.com, ssavla@brocade.com
License: UNKNOWN
Platform: UNKNOWN
Classifier: Development Status :: 5 - Production/Stable
Classifier: Intended Audience :: Developers
Classifier: License :: OSI Approved :: Apache Software License
Classifier: Operating System :: OS Independent
Classifier: Programming Language :: Python
Classifier: Programming Language :: Python :: 2.7
Classifier: Topic :: Software Development :: Libraries
Classifier: Topic :: Software Development :: Libraries :: Python Modules
Classifier: Topic :: System :: Networking
